lilcom_extension.cpython-311-x86_64-linux-gnu.so
lilcom/__init__.py
lilcom/lilcom_interface.py
lilcom-1.8.2.dist-info/METADATA
lilcom-1.8.2.dist-info/WHEEL
lilcom-1.8.2.dist-info/top_level.txt
lilcom-1.8.2.dist-info/RECORD
lilcom-1.8.2.dist-info/licenses/LICENSE
