Metadata-Version: 2.4
Name: lilcom
Version: 1.8.2
Summary: Lossy-compression utility for sequence data in NumPy
Home-page: https://github.com/danpovey/lilcom
Author: Daniel Povey, Meixu Song, Soroush Zargar, Mahsa Yarmohammadi, Jian Wu
Author-email: dpovey@gmail.com
License: MIT
Keywords: compression numpy
Classifier: Development Status :: 4 - Beta
Classifier: Programming Language :: Python :: 3
Classifier: Topic :: System :: Archiving :: Compression
Classifier: License :: OSI Approved :: MIT License
Requires-Python: >=3.6
License-File: LICENSE
Requires-Dist: numpy
Dynamic: author
Dynamic: author-email
Dynamic: classifier
Dynamic: description
Dynamic: description-content-type
Dynamic: home-page
Dynamic: keywords
Dynamic: license
Dynamic: license-file
Dynamic: requires-dist
Dynamic: requires-python
Dynamic: summary
